<?xml version="1.0"?>
<tryton>
<data depends="stock">

  <!-- Delivery_note -->
  <record model='html.template' id="delivery_note_template_id">
      <field name="name">Delivery Note</field>
      <field name="type">base</field>
      <field name="sequence" eval="99"/>
      <field name="filename">html_report/stock/templates/delivery_note.html</field>
  </record>

  <record model='html.template.signature' id="stock_moves_macro_signature">
      <field name="name">show_stock_moves(document, valued)</field>
  </record>
  <record model='html.template' id="stock_moves_macro_id">
      <field name="name">Stock Moves</field>
      <field name="type">macro</field>
      <field name="sequence" eval="99"/>
      <field name="filename">html_report/stock/templates/stock_moves_macro.html</field>
      <field name="implements" ref="html_report.stock_moves_macro_signature"/>
  </record>

  <record model='html.template' id="delivery_note_document_info_macro_id">
      <field name="name">Delivery Note Document info</field>
      <field name="type">macro</field>
      <field name="sequence" eval="99"/>
      <field name="filename">html_report/stock/templates/delivery_note_document_info_macro.html</field>
      <field name="implements" ref="html_report.document_info_macro_signature"/>
  </record>

  <record model="ir.action.report" id="stock.report_shipment_out_delivery_note">
      <field name="active" eval="False"/>
  </record>

  <record model="ir.action.report" id="html_report_delivery_note">
      <field name="name">Delivery Note</field>
      <field name="model">stock.shipment.out</field>
      <field name="report_name">stock.shipment.out.delivery_note</field>
      <field name="extension">pdf</field>
      <field name="template_extension">jinja</field>
      <field name="single" eval="True"/>
      <field name="html_template" ref="delivery_note_template_id"/>
      <field name="html_header_template" ref="header_template"/>
      <field name="html_footer_template" ref="footer_template"/>
      <field name="extension">pdf</field>
  </record>

  <record model="ir.action.keyword" id="report_delivery_note_keyword">
      <field name="keyword">form_print</field>
      <field name="model">stock.shipment.out,-1</field>
      <field name="action" ref="html_report_delivery_note"/>
  </record>


  <record model="html.report.template" id="report_delivery_note_show_image_id">
    <field name="report" ref="html_report_delivery_note"/>
    <field name="signature" ref="show_image_signature"/>
  </record>

  <record model="html.report.template" id="report_delivery_note_company_id">
    <field name="report" ref="html_report_delivery_note"/>
    <field name="signature" ref="company_info_macro_signature"/>
  </record>

  <record model="html.report.template" id="report_delivery_note_stock_moves_id">
    <field name="report" ref="html_report_delivery_note"/>
    <field name="signature" ref="stock_moves_macro_signature"/>
  </record>

  <record model="html.report.template" id="report_delivery_note_delivery_note_party_id">
    <field name="report" ref="html_report_delivery_note"/>
    <field name="signature" ref="party_macro_signature"/>
  </record>

  <record model="html.report.template" id="report_delivery_note_document_id">
    <field name="report" ref="html_report_delivery_note"/>
    <field name="signature" ref="document_info_macro_signature"/>
    <field name="template" ref="delivery_note_document_info_macro_id"/>
  </record>

  <record model="html.report.template" id="report_delivery_note_footer_id">
    <field name="report" ref="html_report_delivery_note"/>
    <field name="signature" ref="show_footer_signature"/>
  </record>
</data>

<data depends="stock_valued">
    <!-- Valued delivery_note -->
    <record model='html.template' id="valued_delivery_note_template_id">
        <field name="name">Valued Delivery Note</field>
        <field name="type">base</field>
        <field name="sequence" eval="99"/>
        <field name="filename">html_report/stock/templates/valued_delivery_note.html</field>
    </record>

   <record model='html.template' id="valued_delivery_note_last_footer_template">
       <field name="name">Valued Delivery Note Last Footer</field>
       <field name="type">footer</field>
       <field name="sequence" eval="99"/>
       <field name="filename">html_report/stock/templates/valued_delivery_note_last_footer.html</field>
   </record>

  <record model="ir.action.report" id="html_report_valued_delivery_note">
      <field name="name">Valued Delivery Note</field>
      <field name="model">stock.shipment.out</field>
      <field name="report_name">stock.shipment.out.valued_delivery_note</field>
      <field name="extension">pdf</field>
      <field name="template_extension">jinja</field>
      <field name="single" eval="True"/>
      <field name="html_template" ref="valued_delivery_note_template_id"/>
      <field name="html_header_template" ref="header_template"/>
      <field name="html_footer_template" ref="footer_template"/>
      <field name="html_last_footer_template" ref="valued_delivery_note_last_footer_template"/>
      <field name="extension">pdf</field>
  </record>

  <record model="ir.action.keyword" id="report_valued_delivery_note_keyword">
      <field name="keyword">form_print</field>
      <field name="model">stock.shipment.out,-1</field>
      <field name="action" ref="html_report_valued_delivery_note"/>
  </record>

  <record model="html.report.template" id="report_valued_delivery_note_company_id">
    <field name="report" ref="html_report_valued_delivery_note"/>
    <field name="signature" ref="company_info_macro_signature"/>
  </record>

  <record model="html.report.template" id="report_valued_delivery_note_show_image_id">
    <field name="report" ref="html_report_valued_delivery_note"/>
    <field name="signature" ref="show_image_signature"/>
  </record>

  <record model="html.report.template" id="report_valued_delivery_note_stock_moves_id">
    <field name="report" ref="html_report_valued_delivery_note"/>
    <field name="signature" ref="stock_moves_macro_signature"/>
  </record>

  <record model="html.report.template" id="report_valued_delivery_note_delivery_note_party_id">
    <field name="report" ref="html_report_valued_delivery_note"/>
    <field name="signature" ref="party_macro_signature"/>
  </record>

  <record model="html.report.template" id="t">
    <field name="report" ref="html_report_valued_delivery_note"/>
    <field name="signature" ref="document_info_macro_signature"/>
    <field name="template" ref="delivery_note_document_info_macro_id"/>
  </record>

  <record model="html.report.template" id="report_valued_delivery_note_totals_id">
    <field name="report" ref="html_report_valued_delivery_note"/>
    <field name="signature" ref="document_totals_macro_signature"/>
  </record>
  <record model="html.report.template" id="report_valued_delivery_note_footer_id">
    <field name="report" ref="html_report_valued_delivery_note"/>
    <field name="signature" ref="show_footer_signature"/>
  </record>
</data>

<data depends="carrier,stock">
  <record model="html.report.template" id="report_delivery_note_show_carrier_id">
    <field name="report" ref="html_report_delivery_note"/>
    <field name="signature" ref="show_carrier_signature"/>
  </record>
</data>

<data depends="carrier,stock_valued">
   <record model="html.report.template" id="report_delivery_note_valued_show_carrier_id">
    <field name="report" ref="html_report_valued_delivery_note"/>
    <field name="signature" ref="show_carrier_signature"/>
  </record>
</data>
</tryton>
